retrolab/__init__.py
retrolab/__main__.py
retrolab/_version.py
retrolab/app.py
retrolab/serverextension.py
retrolab/labextension/package.json
retrolab/labextension/schemas/@retrolab/lab-extension/interface-switcher.json
retrolab/labextension/schemas/@retrolab/lab-extension/package.json.orig
retrolab/labextension/static/568.43e96248ddabebd7d8c1.js
retrolab/labextension/static/676.4ced5e44813c465d9d0d.js
retrolab/labextension/static/697.212c1d6546c1a066a01f.js
retrolab/labextension/static/776.d2dd2c76842bf87de493.js
retrolab/labextension/static/974.a57245c4538e552cf996.js
retrolab/labextension/static/remoteEntry.c8410055f1a8098c2874.js
retrolab/labextension/static/style.js
retrolab/labextension/static/third-party-licenses.json
retrolab/schemas/@retrolab/application-extension/menus.json
retrolab/schemas/@retrolab/application-extension/package.json.orig
retrolab/schemas/@retrolab/application-extension/top.json
retrolab/schemas/@retrolab/notebook-extension/package.json.orig
retrolab/schemas/@retrolab/notebook-extension/scroll-output.json
retrolab/static/0c6bfc668a72935760178f91327aed3a.eot
retrolab/static/1036.bundle.js
retrolab/static/1198.bundle.js
retrolab/static/1336.bundle.js
retrolab/static/1337.bundle.js
retrolab/static/1356.bundle.js
retrolab/static/1382.bundle.js
retrolab/static/143.bundle.js
retrolab/static/1432.bundle.js
retrolab/static/1542.bundle.js
retrolab/static/1542.bundle.js.LICENSE.txt
retrolab/static/157.bundle.js
retrolab/static/1647.bundle.js
retrolab/static/1650.bundle.js
retrolab/static/1682.bundle.js
retrolab/static/1684.bundle.js
retrolab/static/1696.bundle.js
retrolab/static/170.bundle.js
retrolab/static/1782.bundle.js
retrolab/static/1809.bundle.js
retrolab/static/1835.bundle.js
retrolab/static/1867.bundle.js
retrolab/static/1a575a4138e5f366474f0e7c5bd614a5.woff
retrolab/static/2007.bundle.js
retrolab/static/2067.bundle.js
retrolab/static/2088.bundle.js
retrolab/static/2089.bundle.js
retrolab/static/2122.bundle.js
retrolab-0.3.21.dist-info/LICENSE
retrolab-0.3.21.dist-info/METADATA
retrolab-0.3.21.dist-info/WHEEL
retrolab-0.3.21.dist-info/entry_points.txt
retrolab-0.3.21.dist-info/top_level.txt
retrolab-0.3.21.dist-info/RECORD
