Metadata-Version: 2.1
Name: retrolab
Version: 0.3.21
Summary: JupyterLab Distribution with a retro look and feel
Home-page: https://github.com/jupyterlab/retrolab
Author: Jupyter Development Team
Author-email: jupyter@googlegroups.com
License: UNKNOWN
Keywords: Jupyter,JupyterLab,Notebook
Platform: Linux
Platform: Mac OS X
Platform: Windows
Classifier: Intended Audience :: Developers
Classifier: Intended Audience :: System Administrators
Classifier: Intended Audience :: Science/Research
Classifier: License :: OSI Approved :: BSD License
Classifier: Programming Language :: Python
Classifier: Programming Language :: Python :: 3.7
Classifier: Programming Language :: Python :: 3.8
Classifier: Programming Language :: Python :: 3.9
Classifier: Programming Language :: Python :: 3.10
Classifier: Framework :: Jupyter
Requires-Python: >=3.7
License-File: LICENSE
Requires-Dist: jupyterlab (~=3.4.0)
Requires-Dist: jupyterlab-server (~=2.3)
Requires-Dist: jupyter-server (~=1.4)
Requires-Dist: nbclassic (~=0.2)
Requires-Dist: tornado (>=6.1.0)
